[
    {
        "Research Interest": "Missing",
        "Name": "Joanna Aizenberg",
        "Position": "Missing"
    },
    {
        "Research Interest": "Missing",
        "Name": "Ariel Amir",
        "Position": "Missing"
    },
    {
        "Research Interest": "Missing",
        "Name": "Michael J. Aziz",
        "Position": "Missing"
    },
    {
        "Research Interest": "Missing",
        "Name": "David C. Bell",
        "Position": "Missing"
    },
    {
        "Research Interest": "Missing",
        "Name": "Katia Bertoldi",
        "Position": "Missing"
    },
    {
        "Research Interest": "Missing",
        "Name": "Joze Bevk",
        "Position": "Missing"
    },
    {
        "Research Interest": "Missing",
        "Name": "David Clarke",
        "Position": "Missing"
    },
    {
        "Research Interest": "Missing",
        "Name": "Cynthia Friend",
        "Position": "Missing"
    },
    {
        "Research Interest": "Missing",
        "Name": "Roy G. Gordon",
        "Position": "Missing"
    },
    {
        "Research Interest": "Missing",
        "Name": "Jenny Hoffman",
        "Position": "Missing"
    },
    {
        "Research Interest": "Missing",
        "Name": "Evelyn Hu",
        "Position": "Missing"
    },
    {
        "Research Interest": "Missing",
        "Name": "Efthimios Kaxiras",
        "Position": "Missing"
    },
    {
        "Research Interest": "Missing",
        "Name": "Philip Kim",
        "Position": "Missing"
    },
    {
        "Research Interest": "Missing",
        "Name": "Boris Kozinsky",
        "Position": "Missing"
    },
    {
        "Research Interest": "Missing",
        "Name": "Jennifer Lewis",
        "Position": "Missing"
    },
    {
        "Research Interest": "Missing",
        "Name": "Xin Li",
        "Position": "Missing"
    },
    {
        "Research Interest": "Missing",
        "Name": "Charles M. Lieber",
        "Position": "Missing"
    },
    {
        "Research Interest": "Missing",
        "Name": "Jia Liu",
        "Position": "Missing"
    },
    {
        "Research Interest": "Missing",
        "Name": "Vinothan N. Manoharan",
        "Position": "Missing"
    },
    {
        "Research Interest": "Missing",
        "Name": "Samir Mitragotri",
        "Position": "Missing"
    },
    {
        "Research Interest": "Missing",
        "Name": "Julia A. Mundy",
        "Position": "Missing"
    },
    {
        "Research Interest": "Missing",
        "Name": "Prineha Narang",
        "Position": "Missing"
    },
    {
        "Research Interest": "Missing",
        "Name": "Venkatesh Narayanamurti",
        "Position": "Missing"
    },
    {
        "Research Interest": "Missing",
        "Name": "Daniel Needleman",
        "Position": "Missing"
    },
    {
        "Research Interest": "Missing",
        "Name": "James R. Rice",
        "Position": "Missing"
    },
    {
        "Research Interest": "Missing",
        "Name": "Frans A. Spaepen",
        "Position": "Missing"
    },
    {
        "Research Interest": "Missing",
        "Name": "Zhigang Suo",
        "Position": "Missing"
    },
    {
        "Research Interest": "Missing",
        "Name": "Joost J. Vlassak",
        "Position": "Missing"
    },
    {
        "Research Interest": "Missing",
        "Name": "Conor J Walsh",
        "Position": "Missing"
    },
    {
        "Research Interest": "Missing",
        "Name": "David A. Weitz",
        "Position": "Missing"
    },
    {
        "Research Interest": "Missing",
        "Name": "Joanna Aizenberg",
        "Position": "Missing"
    },
    {
        "Research Interest": "Missing",
        "Name": "Ariel Amir",
        "Position": "Missing"
    },
    {
        "Research Interest": "Missing",
        "Name": "Markus Thomas Basan",
        "Position": "Missing"
    },
    {
        "Research Interest": "Missing",
        "Name": "Michael P. Brenner",
        "Position": "Missing"
    },
    {
        "Research Interest": "Missing",
        "Name": "David Clarke",
        "Position": "Missing"
    },
    {
        "Research Interest": "Missing",
        "Name": "Doeke Romke Hekstra",
        "Position": "Missing"
    },
    {
        "Research Interest": "Missing",
        "Name": "Boris Kozinsky",
        "Position": "Missing"
    },
    {
        "Research Interest": "Missing",
        "Name": "Jennifer Lewis",
        "Position": "Missing"
    },
    {
        "Research Interest": "Missing",
        "Name": "Charles M. Lieber",
        "Position": "Missing"
    },
    {
        "Research Interest": "Missing",
        "Name": "L Mahadevan",
        "Position": "Missing"
    },
    {
        "Research Interest": "Missing",
        "Name": "Vinothan N. Manoharan",
        "Position": "Missing"
    },
    {
        "Research Interest": "Missing",
        "Name": "Daniel Needleman",
        "Position": "Missing"
    },
    {
        "Research Interest": "Missing",
        "Name": "Maxim Prigozhin",
        "Position": "Missing"
    },
    {
        "Research Interest": "Missing",
        "Name": "Sharad Ramanathan",
        "Position": "Missing"
    },
    {
        "Research Interest": "Missing",
        "Name": "Christopher Rycroft",
        "Position": "Missing"
    },
    {
        "Research Interest": "Missing",
        "Name": "Frans A. Spaepen",
        "Position": "Missing"
    },
    {
        "Research Interest": "Missing",
        "Name": "Zhigang Suo",
        "Position": "Missing"
    },
    {
        "Research Interest": "Missing",
        "Name": "Joost J. Vlassak",
        "Position": "Missing"
    },
    {
        "Research Interest": "Missing",
        "Name": "David A. Weitz",
        "Position": "Missing"
    },
    {
        "Research Interest": "Missing",
        "Name": "Joanna Aizenberg",
        "Position": "Missing"
    },
    {
        "Research Interest": "Missing",
        "Name": "Ariel Amir",
        "Position": "Missing"
    },
    {
        "Research Interest": "Missing",
        "Name": "Philippe Cluzel",
        "Position": "Missing"
    },
    {
        "Research Interest": "Missing",
        "Name": "Donhee Ham",
        "Position": "Missing"
    },
    {
        "Research Interest": "Missing",
        "Name": "Charles M. Lieber",
        "Position": "Missing"
    },
    {
        "Research Interest": "Missing",
        "Name": "Jia Liu",
        "Position": "Missing"
    },
    {
        "Research Interest": "Missing",
        "Name": "David R. Nelson",
        "Position": "Missing"
    },
    {
        "Research Interest": "Missing",
        "Name": "Maxim Prigozhin",
        "Position": "Missing"
    },
    {
        "Research Interest": "Missing",
        "Name": "Sharad Ramanathan",
        "Position": "Missing"
    }
]