[
    {
        "Position": "R. Selden Rose Professor of Comparative Literature and Professor of Film Studies",
        "Name": "Dudley Andrew",
        "Email": "dudley.andrew@yale.edu",
        "Phone number": "Phone: (203) 436-4614 ",
        "Research Interest": "Missing"
    },
    {
        "Position": "Lecturer in Art and in Film Studies",
        "Name": "Jonathan Andrews",
        "Email": "jonathan.andrews@yale.edu",
        "Phone number": "Phone: (802) 233-8594 ",
        "Research Interest": "Missing"
    },
    {
        "Position": "Assistant Professor of Slavic Languages &amp; Literatures; Film and Media Studies; Women\\xe2\\x80\\x99s, Gender, &amp; Sexuality Studies",
        "Name": "Marijeta Bozovic",
        "Email": "marijeta.bozovic@yale.edu",
        "Phone number": "Phone: +1 917 887 5197 ",
        "Research Interest": "Missing"
    },
    {
        "Position": "Thomas E. Donnelley Professor of Humanities and Professor of Film Studies",
        "Name": "Francesco Casetti",
        "Email": "francesco.casetti@yale.edu",
        "Phone number": "Phone: (203) 432-0671 ",
        "Research Interest": "Missing"
    },
    {
        "Position": "Associate Research Scholar in Film and Media Studies",
        "Name": "Oksana Chefranova",
        "Email": "oksana.chefranova@yale.edu",
        "Phone number": "oksana.chefranova@yale.edu",
        "Research Interest": "Missing"
    },
    {
        "Position": "Professor of Comparative Literature and of Slavic Languages and Literatures",
        "Name": "Katerina Clark",
        "Email": "katerina.clark@yale.edu",
        "Phone number": "Phone: (203) 432-0712 ",
        "Research Interest": "Missing"
    },
    {
        "Position": "Assistant Professor of Comparative Literature and of English",
        "Name": "Marta Figlerowicz",
        "Email": "marta.figlerowicz@yale.edu",
        "Phone number": "Phone: (203) 432-2763 ",
        "Research Interest": "Missing"
    },
    {
        "Position": "Lecturer in African American Studies and Film &amp; Media Studies ",
        "Name": "Nicholas Forster",
        "Email": "nicholas.forster@yale.edu",
        "Phone number": "nicholas.forster@yale.edu",
        "Research Interest": "Missing"
    },
    {
        "Position": "Professor of Film Studies and of East Asian Languages and Literatures",
        "Name": "Aaron Gerow",
        "Email": "aaron.gerow@yale.edu",
        "Phone number": "Phone: (203) 432-7082 ",
        "Research Interest": "Missing"
    },
    {
        "Position": "Senior Lecturer in African American Studies and Film &amp; Media Studies ",
        "Name": "Thomas Allen Harris",
        "Email": "thomas.allen.harris@yale.edu",
        "Phone number": "thomas.allen.harris@yale.edu",
        "Research Interest": "Missing"
    },
    {
        "Position": "Associate Professor in the Music Department",
        "Name": "Brian Kane",
        "Email": "brian.kane@yale.edu",
        "Phone number": "Phone: (203) 432-6730 ",
        "Research Interest": "Missing"
    },
    {
        "Position": "Senior Lecturer in Film Studies",
        "Name": "Marc Lapadula",
        "Email": "marc.lapadula@yale.edu",
        "Phone number": "Phone: (203) 436-4668 ",
        "Research Interest": "Missing"
    },
    {
        "Position": "Professor of Slavic Languages and Literatures and of Film Studies",
        "Name": "John MacKay",
        "Email": "john.mackay@yale.edu",
        "Phone number": "Phone: (203) 432-7202 ",
        "Research Interest": "Missing"
    },
    {
        "Position": "Professor of Italian Language and Literature",
        "Name": "Millicent Marcus",
        "Email": "millicent.marcus@yale.edu",
        "Phone number": "Phone: (203) 432-0599 ",
        "Research Interest": "Missing"
    },
    {
        "Position": "Archive &amp; Special Collection Manager, Yale Film Study Center",
        "Name": "Brian Meacham",
        "Email": "brian.meacham@yale.edu",
        "Phone number": "Phone: (203) 432-2798 ",
        "Research Interest": "Missing"
    },
    {
        "Position": "Professor of American Studies, Film Studies, and Theater Studies",
        "Name": "Charles Musser",
        "Email": "charles.musser@yale.edu",
        "Phone number": "Phone: (203) 432-0152 ",
        "Research Interest": "Missing"
    },
    {
        "Position": "Professor of Germanic Languages &amp; Literatures",
        "Name": "Fatima Naqvi",
        "Email": "fatima.naqvi@yale.edu",
        "Phone number": "fatima.naqvi@yale.edu",
        "Research Interest": "Missing"
    },
    {
        "Position": "Maria Rosa Menocal Professor of English and of Film and Media Studies",
        "Name": "John Durham Peters",
        "Email": "john.peters@yale.edu",
        "Phone number": "Phone: (203) 432-6894 ",
        "Research Interest": "Missing"
    },
    {
        "Position": "Elias Leavenworth Professor of German; Professor of Film and Media Studies",
        "Name": "Brigitte Peucker",
        "Email": "brigitte.peucker@yale.edu",
        "Phone number": "Phone: (203) 432-0785 ",
        "Research Interest": "Missing"
    },
    {
        "Position": "Lecturer, Film and Media Studies ",
        "Name": "Camille Thomasson",
        "Email": "camille.thomasson@yale.edu",
        "Phone number": "camille.thomasson@yale.edu",
        "Research Interest": "Missing"
    },
    {
        "Position": "Emily Sanford Professor of Comparative Literature and Professor of English",
        "Name": "Katie Trumpener",
        "Email": "katie.trumpener@yale.edu",
        "Phone number": "Phone: (203) 432-7674 ",
        "Research Interest": "Missing"
    },
    {
        "Position": "Professor of East Asian Languages and Literatures and of Comparative Literature",
        "Name": "Jing Tsu",
        "Email": "jing.tsu@yale.edu",
        "Phone number": "Phone: (203) 432-2861 ",
        "Research Interest": "Missing"
    },
    {
        "Position": "Laura Wexler Professor of American Studies Professor of Women&#039;s, Gender &amp; Sexuality Studies, Professor of Film &amp; Media Studies Affiliate Faculty, Ethnicity, Race &amp; Migration Co-Chair, Public Humanities Program Director, The Photographic Memory Workshop at Yale P. I., The Photogrammar Project photogrammar.yale.edu",
        "Name": "Laura Wexler",
        "Email": "laura.wexler@yale.edu",
        "Phone number": "Phone: (203) 432-1524 ",
        "Research Interest": "Missing"
    },
    {
        "Position": "Associate Professor of English and of Film Studies",
        "Name": "R. John Williams",
        "Email": "robert.j.williams@yale.edu",
        "Phone number": "Phone: (203) 432-2237 ",
        "Research Interest": "Missing"
    }
]